Metadata-Version: 2.4
Name: tale-suite
Version: 1.0.0rc2
Summary: TALES: Text-Adventure Learning Environment Suite
Project-URL: Homepage, https://github.com/microsoft/tale-suite
Project-URL: Bug Tracker, https://github.com/microsoft/tale-suite/issues
Classifier: Programming Language :: Python :: 3
Classifier: License :: OSI Approved :: MIT License
Classifier: Operating System :: OS Independent
Requires-Python: >=3.12
License-File: LICENSE
Requires-Dist: tatsu==5.8.3
Requires-Dist: gymnasium>=1.0.0
Requires-Dist: jericho>=3.3.0
Requires-Dist: textworld[pddl]>=1.6.2rc3
Requires-Dist: textworld-express>=1.1.0rc5
Requires-Dist: scienceworld>=1.2.2
Requires-Dist: discoveryworld
Requires-Dist: alfworld>=0.4.0
Requires-Dist: termcolor
Requires-Dist: wandb
Requires-Dist: numpy
Requires-Dist: pandas
Requires-Dist: llm>=0.27.1
Requires-Dist: llm-anthropic
Requires-Dist: llm-gemini
Requires-Dist: llm-azure-openai
Requires-Dist: anthropic
Requires-Dist: google-genai
Requires-Dist: tiktoken>=0.11.0
Requires-Dist: tenacity
Requires-Dist: transformers
Provides-Extra: dev
Requires-Dist: pytest; extra == "dev"
Requires-Dist: pre-commit; extra == "dev"
Requires-Dist: black; extra == "dev"
Requires-Dist: isort; extra == "dev"
Dynamic: license-file
